responsibly/__init__.py
responsibly/__main__.py
responsibly/cli.py
responsibly/consts.py
responsibly/utils.py
responsibly/dataset/__init__.py
responsibly/dataset/core.py
responsibly/dataset/adult/__init__.py
responsibly/dataset/adult/adult.data
responsibly/dataset/adult/adult.names
responsibly/dataset/adult/adult.test
responsibly/dataset/compas/__init__.py
responsibly/dataset/compas/compas-scores-two-years.csv
responsibly/dataset/fico/__init__.py
responsibly/dataset/fico/totals.csv
responsibly/dataset/fico/transrisk_cdf_by_race_ssa.csv
responsibly/dataset/fico/transrisk_performance_by_race_ssa.csv
responsibly/dataset/german/__init__.py
responsibly/dataset/german/german.data
responsibly/dataset/german/values_maps.json
responsibly/fairness/__init__.py
responsibly/fairness/interventions/__init__.py
responsibly/fairness/interventions/threshold.py
responsibly/fairness/metrics/__init__.py
responsibly/fairness/metrics/binary.py
responsibly/fairness/metrics/score.py
responsibly/fairness/metrics/utils.py
responsibly/fairness/metrics/visualization.py
responsibly/tests/__init__.py
responsibly/tests/conftest.py
responsibly/tests/data.py
responsibly/tests/test_dataset.py
responsibly/tests/test_fairness.py
responsibly/tests/test_we.py
responsibly/tests/utils.py
responsibly/we/__init__.py
responsibly/we/benchmark.py
responsibly/we/bias.py
responsibly/we/utils.py
responsibly/we/weat.py
responsibly/we/data/GoogleNews-vectors-negative300-bolukbasi.bin
responsibly/we/data/__init__.py
responsibly/we/data/_extract_caliskan.py
responsibly/we/data/bolukbasi.json
responsibly/we/data/occupational_female_precentage.json
responsibly/we/data/weat.json
responsibly/we/data/benchmark/MEN_dataset_natural_form_full.tsv
responsibly/we/data/benchmark/MSR-syntax.txt
responsibly/we/data/benchmark/MTURK-771.tsv
responsibly/we/data/benchmark/RG_word.tsv
responsibly/we/data/benchmark/SimLex-999.tsv
responsibly/we/data/benchmark/TermRelatednessResults.tsv
responsibly/we/data/benchmark/questions-words.txt
responsibly-0.1.3.dist-info/LICENSE
responsibly-0.1.3.dist-info/METADATA
responsibly-0.1.3.dist-info/WHEEL
responsibly-0.1.3.dist-info/top_level.txt
responsibly-0.1.3.dist-info/RECORD
