Metadata-Version: 2.1
Name: responsibly
Version: 0.1.3
Summary: Toolkit for Auditing and Mitigating Bias and Fairness of Machine Learning Systems 🔎🤖🧰
Home-page: https://docs.responsibly.ai
Author: Shlomi Hod
Author-email: shlomi.hod@gmail.com
License: MIT
Platform: UNKNOWN
Classifier: Development Status :: 4 - Beta
Classifier: Intended Audience :: Science/Research
Classifier: Topic :: Scientific/Engineering :: Artificial Intelligence
Classifier: Topic :: Text Processing :: Linguistic
Classifier: License :: OSI Approved :: MIT License
Classifier: Natural Language :: English
Classifier: Operating System :: OS Independent
Classifier: Programming Language :: Python
Classifier: Programming Language :: Python :: 3
Classifier: Programming Language :: Python :: 3 :: Only
Classifier: Programming Language :: Python :: 3.6
Classifier: Programming Language :: Python :: 3.7
Requires-Python: >=3.6, <3.9
Requires-Dist: numpy (>=1.15)
Requires-Dist: scipy (>=1.1)
Requires-Dist: pandas (>=0.23)
Requires-Dist: matplotlib (<3,>=2.2)
Requires-Dist: seaborn (>=0.9)
Requires-Dist: scikit-learn (>=0.19)
Requires-Dist: gensim (<3.8,>=3.7)
Requires-Dist: tabulate (>=0.8)
Requires-Dist: six (>=1.10)
Requires-Dist: click (>=6.0)
Requires-Dist: tqdm (>=4.24)
Requires-Dist: mlxtend (<0.17,>=0.13)
